webling_calendar/__init__.py
webling_calendar/__main__.py
webling_calendar/api.py
webling_calendar/calendarevent.py
webling_calendar/cli.py
webling_calendar/config.py
webling_calendar/event.py
webling_calendar/ics_reader.py
webling_calendar-0.1.0.dist-info/LICENSE
webling_calendar-0.1.0.dist-info/METADATA
webling_calendar-0.1.0.dist-info/WHEEL
webling_calendar-0.1.0.dist-info/entry_points.txt
webling_calendar-0.1.0.dist-info/top_level.txt
webling_calendar-0.1.0.dist-info/RECORD
