Metadata-Version: 2.1
Name: webling-calendar
Version: 0.1.0
Summary: Awesome webling_calendar created by dimschlukas
Home-page: https://github.com/dimschlukas/webling-calendar/
Author: dimschlukas
License-File: LICENSE
Requires-Dist: click
Requires-Dist: requests
Requires-Dist: types-requests
Requires-Dist: python-dotenv
Requires-Dist: icalendar
Provides-Extra: test
Requires-Dist: pytest ; extra == 'test'
Requires-Dist: coverage ; extra == 'test'
Requires-Dist: flake8 ; extra == 'test'
Requires-Dist: black ; extra == 'test'
Requires-Dist: isort ; extra == 'test'
Requires-Dist: pytest-cov ; extra == 'test'
Requires-Dist: mypy ; extra == 'test'
Requires-Dist: gitchangelog ; extra == 'test'
Requires-Dist: mkdocs ; extra == 'test'
